[
  {
    "area_id": 1583,
    "banner": 930189,
    "difficulty": 1,
    "id": 901583011,
    "name": "運命の回廊 1層～10層",
    "name_en": "Corridor of Fate 1st to 10th floors",
    "name_en_src": "ml",
    "sort_order": 1
  },
  {
    "area_id": 1583,
    "banner": 930189,
    "difficulty": 1,
    "id": 901583111,
    "name": "運命の回廊 11層～18層",
    "name_en": "Corridor of Fate floors 11-18",
    "name_en_src": "ml",
    "sort_order": 2
  },
  {
    "area_id": 1583,
    "banner": 930189,
    "difficulty": 1,
    "id": 901583191,
    "name": "運命の回廊 19層～27層",
    "name_en": "Corridor of Fate 19-27 floors",
    "name_en_src": "ml",
    "sort_order": 3
  },
  {
    "area_id": 1583,
    "banner": 930189,
    "difficulty": 1,
    "id": 901583281,
    "name": "運命の回廊 28層～35層",
    "name_en": "Corridor of Fate 28-35",
    "name_en_src": "ml",
    "sort_order": 4
  },
  {
    "area_id": 1583,
    "banner": 930189,
    "difficulty": 1,
    "id": 901583361,
    "name": "運命の回廊 36層～43層",
    "name_en": "Corridor of Fate 36-43 floors",
    "name_en_src": "ml",
    "sort_order": 5
  },
  {
    "area_id": 1583,
    "banner": 930189,
    "difficulty": 1,
    "id": 901583441,
    "name": "運命の回廊 特別層",
    "name_en": "Corridor of Fate special tier",
    "name_en_src": "ml",
    "sort_order": 6
  }
]