[
  {
    "id": 900100,
    "panel_shop_id": 909001,
    "step": 1,
    "panel_illust_id": 100004,
    "loop": 0,
    "step_reward_type": 1,
    "step_reward_id": 100002,
    "step_reward_quantity": 1000,
    "lucky_reward_box_id": 100001,
    "panel_shop_product_ids": [
      900101,
      900102,
      900103,
      900104,
      900105,
      900106,
      900107,
      900108,
      900109,
      900110,
      900111,
      900112,
      900113,
      900114,
      900115,
      900116
    ]
  },
  {
    "id": 900200,
    "panel_shop_id": 909001,
    "step": 2,
    "panel_illust_id": 100005,
    "loop": 0,
    "step_reward_type": 2,
    "step_reward_id": 105001,
    "step_reward_quantity": 100,
    "lucky_reward_box_id": 100001,
    "panel_shop_product_ids": [
      900201,
      900202,
      900203,
      900204
    ]
  },
  {
    "id": 900300,
    "panel_shop_id": 909001,
    "step": 3,
    "panel_illust_id": 100006,
    "loop": 0,
    "step_reward_type": 1,
    "step_reward_id": 100002,
    "step_reward_quantity": 1000,
    "lucky_reward_box_id": 100001,
    "panel_shop_product_ids": [
      900301,
      900302,
      900303,
      900304
    ]
  },
  {
    "id": 900400,
    "panel_shop_id": 909001,
    "step": 4,
    "panel_illust_id": 100007,
    "loop": 0,
    "step_reward_type": 2,
    "step_reward_id": 105001,
    "step_reward_quantity": 100,
    "lucky_reward_box_id": 100001,
    "panel_shop_product_ids": [
      900401,
      900402,
      900403,
      900404
    ]
  },
  {
    "id": 900500,
    "panel_shop_id": 909001,
    "step": 5,
    "panel_illust_id": 100008,
    "loop": 0,
    "step_reward_type": 1,
    "step_reward_id": 100002,
    "step_reward_quantity": 1000,
    "lucky_reward_box_id": 100001,
    "panel_shop_product_ids": [
      900501,
      900502,
      900503,
      900504
    ]
  },
  {
    "id": 900600,
    "panel_shop_id": 909001,
    "step": 6,
    "panel_illust_id": 100009,
    "loop": 0,
    "step_reward_type": 2,
    "step_reward_id": 105001,
    "step_reward_quantity": 50,
    "lucky_reward_box_id": 100001,
    "panel_shop_product_ids": [
      900601,
      900602,
      900603,
      900604
    ]
  },
  {
    "id": 900700,
    "panel_shop_id": 909001,
    "step": 7,
    "panel_illust_id": 100010,
    "loop": 0,
    "step_reward_type": 1,
    "step_reward_id": 100002,
    "step_reward_quantity": 1000,
    "lucky_reward_box_id": 100001,
    "panel_shop_product_ids": [
      900701,
      900702,
      900703,
      900704
    ]
  },
  {
    "id": 900800,
    "panel_shop_id": 909001,
    "step": 8,
    "panel_illust_id": 100011,
    "loop": 0,
    "step_reward_type": 2,
    "step_reward_id": 105001,
    "step_reward_quantity": 50,
    "lucky_reward_box_id": 100001,
    "panel_shop_product_ids": [
      900801,
      900802,
      900803,
      900804
    ]
  },
  {
    "id": 900900,
    "panel_shop_id": 909001,
    "step": 9,
    "panel_illust_id": 100012,
    "loop": 0,
    "step_reward_type": 1,
    "step_reward_id": 100002,
    "step_reward_quantity": 1000,
    "lucky_reward_box_id": 100001,
    "panel_shop_product_ids": [
      900901,
      900902,
      900903,
      900904
    ]
  },
  {
    "id": 901000,
    "panel_shop_id": 909001,
    "step": 10,
    "panel_illust_id": 100013,
    "loop": 0,
    "step_reward_type": 2,
    "step_reward_id": 105001,
    "step_reward_quantity": 50,
    "lucky_reward_box_id": 100001,
    "panel_shop_product_ids": [
      901001,
      901002,
      901003,
      901004,
      901005,
      901006,
      901007,
      901008,
      901009,
      901010,
      901011,
      901012,
      901013,
      901014,
      901015,
      901016
    ]
  },
  {
    "id": 901100,
    "panel_shop_id": 909001,
    "step": 11,
    "panel_illust_id": 100014,
    "loop": 0,
    "step_reward_type": 20,
    "step_reward_id": 881003,
    "step_reward_quantity": 24,
    "lucky_reward_box_id": 100001,
    "panel_shop_product_ids": [
      901101,
      901102,
      901103,
      901104,
      901105,
      901106,
      901107,
      901108,
      901109
    ]
  },
  {
    "id": 901200,
    "panel_shop_id": 909001,
    "step": 12,
    "panel_illust_id": 100015,
    "loop": 0,
    "step_reward_type": 2,
    "step_reward_id": 105001,
    "step_reward_quantity": 50,
    "lucky_reward_box_id": 100001,
    "panel_shop_product_ids": [
      901201,
      901202,
      901203,
      901204,
      901205,
      901206,
      901207,
      901208,
      901209
    ]
  },
  {
    "id": 901300,
    "panel_shop_id": 909001,
    "step": 13,
    "panel_illust_id": 100016,
    "loop": 0,
    "step_reward_type": 20,
    "step_reward_id": 881004,
    "step_reward_quantity": 24,
    "lucky_reward_box_id": 100001,
    "panel_shop_product_ids": [
      901301,
      901302,
      901303,
      901304,
      901305,
      901306,
      901307,
      901308,
      901309
    ]
  },
  {
    "id": 901400,
    "panel_shop_id": 909001,
    "step": 14,
    "panel_illust_id": 100017,
    "loop": 0,
    "step_reward_type": 2,
    "step_reward_id": 105001,
    "step_reward_quantity": 50,
    "lucky_reward_box_id": 100001,
    "panel_shop_product_ids": [
      901401,
      901402,
      901403,
      901404,
      901405,
      901406,
      901407,
      901408,
      901409
    ]
  },
  {
    "id": 901500,
    "panel_shop_id": 909001,
    "step": 15,
    "panel_illust_id": 100018,
    "loop": 0,
    "step_reward_type": 20,
    "step_reward_id": 881003,
    "step_reward_quantity": 24,
    "lucky_reward_box_id": 100001,
    "panel_shop_product_ids": [
      901501,
      901502,
      901503,
      901504,
      901505,
      901506,
      901507,
      901508,
      901509
    ]
  },
  {
    "id": 901600,
    "panel_shop_id": 909001,
    "step": 16,
    "panel_illust_id": 100019,
    "loop": 0,
    "step_reward_type": 2,
    "step_reward_id": 105001,
    "step_reward_quantity": 50,
    "lucky_reward_box_id": 100001,
    "panel_shop_product_ids": [
      901601,
      901602,
      901603,
      901604,
      901605,
      901606,
      901607,
      901608,
      901609
    ]
  },
  {
    "id": 901700,
    "panel_shop_id": 909001,
    "step": 17,
    "panel_illust_id": 100020,
    "loop": 0,
    "step_reward_type": 20,
    "step_reward_id": 881004,
    "step_reward_quantity": 12,
    "lucky_reward_box_id": 100001,
    "panel_shop_product_ids": [
      901701,
      901702,
      901703,
      901704,
      901705,
      901706,
      901707,
      901708,
      901709
    ]
  },
  {
    "id": 901800,
    "panel_shop_id": 909001,
    "step": 18,
    "panel_illust_id": 100021,
    "loop": 0,
    "step_reward_type": 2,
    "step_reward_id": 105001,
    "step_reward_quantity": 50,
    "lucky_reward_box_id": 100001,
    "panel_shop_product_ids": [
      901801,
      901802,
      901803,
      901804,
      901805,
      901806,
      901807,
      901808,
      901809
    ]
  },
  {
    "id": 901900,
    "panel_shop_id": 909001,
    "step": 19,
    "panel_illust_id": 100022,
    "loop": 0,
    "step_reward_type": 20,
    "step_reward_id": 881004,
    "step_reward_quantity": 12,
    "lucky_reward_box_id": 100001,
    "panel_shop_product_ids": [
      901901,
      901902,
      901903,
      901904,
      901905,
      901906,
      901907,
      901908,
      901909
    ]
  },
  {
    "id": 902000,
    "panel_shop_id": 909001,
    "step": 20,
    "panel_illust_id": 100023,
    "loop": 0,
    "step_reward_type": 2,
    "step_reward_id": 105001,
    "step_reward_quantity": 50,
    "lucky_reward_box_id": 100001,
    "panel_shop_product_ids": [
      902001,
      902002,
      902003,
      902004,
      902005,
      902006,
      902007,
      902008,
      902009
    ]
  },
  {
    "id": 902100,
    "panel_shop_id": 909001,
    "step": 21,
    "panel_illust_id": 0,
    "loop": 1,
    "step_reward_type": 2,
    "step_reward_id": 105001,
    "step_reward_quantity": 5,
    "lucky_reward_box_id": 100001,
    "panel_shop_product_ids": [
      902101,
      902102,
      902103,
      902104
    ]
  },
  {
    "id": 902200,
    "panel_shop_id": 909002,
    "step": 1,
    "panel_illust_id": 100024,
    "loop": 0,
    "step_reward_type": 1,
    "step_reward_id": 100002,
    "step_reward_quantity": 3000,
    "lucky_reward_box_id": 100002,
    "panel_shop_product_ids": [
      902201,
      902202,
      902203,
      902204,
      902205,
      902206,
      902207,
      902208,
      902209
    ]
  },
  {
    "id": 902300,
    "panel_shop_id": 909003,
    "step": 1,
    "panel_illust_id": 100025,
    "loop": 0,
    "step_reward_type": 1,
    "step_reward_id": 100002,
    "step_reward_quantity": 3000,
    "lucky_reward_box_id": 100003,
    "panel_shop_product_ids": [
      902301,
      902302,
      902303,
      902304
    ]
  },
  {
    "id": 902400,
    "panel_shop_id": 909003,
    "step": 2,
    "panel_illust_id": 100026,
    "loop": 0,
    "step_reward_type": 33,
    "step_reward_id": 960001,
    "step_reward_quantity": 300,
    "lucky_reward_box_id": 100003,
    "panel_shop_product_ids": [
      902401,
      902402,
      902403,
      902404
    ]
  },
  {
    "id": 902500,
    "panel_shop_id": 909003,
    "step": 3,
    "panel_illust_id": 100027,
    "loop": 0,
    "step_reward_type": 8,
    "step_reward_id": 810066,
    "step_reward_quantity": 100,
    "lucky_reward_box_id": 100003,
    "panel_shop_product_ids": [
      902501,
      902502,
      902503,
      902504
    ]
  },
  {
    "id": 902600,
    "panel_shop_id": 909003,
    "step": 4,
    "panel_illust_id": 100028,
    "loop": 0,
    "step_reward_type": 33,
    "step_reward_id": 960001,
    "step_reward_quantity": 300,
    "lucky_reward_box_id": 100003,
    "panel_shop_product_ids": [
      902601,
      902602,
      902603,
      902604
    ]
  },
  {
    "id": 902700,
    "panel_shop_id": 909003,
    "step": 5,
    "panel_illust_id": 100029,
    "loop": 0,
    "step_reward_type": 1,
    "step_reward_id": 100002,
    "step_reward_quantity": 500,
    "lucky_reward_box_id": 100003,
    "panel_shop_product_ids": [
      902701,
      902702,
      902703,
      902704
    ]
  },
  {
    "id": 902800,
    "panel_shop_id": 909003,
    "step": 6,
    "panel_illust_id": 100030,
    "loop": 0,
    "step_reward_type": 32,
    "step_reward_id": 950012,
    "step_reward_quantity": 50,
    "lucky_reward_box_id": 100003,
    "panel_shop_product_ids": [
      902801,
      902802,
      902803,
      902804
    ]
  },
  {
    "id": 902900,
    "panel_shop_id": 909003,
    "step": 7,
    "panel_illust_id": 100031,
    "loop": 0,
    "step_reward_type": 33,
    "step_reward_id": 960001,
    "step_reward_quantity": 300,
    "lucky_reward_box_id": 100003,
    "panel_shop_product_ids": [
      902901,
      902902,
      902903,
      902904
    ]
  },
  {
    "id": 903000,
    "panel_shop_id": 909003,
    "step": 8,
    "panel_illust_id": 100032,
    "loop": 0,
    "step_reward_type": 32,
    "step_reward_id": 950012,
    "step_reward_quantity": 50,
    "lucky_reward_box_id": 100003,
    "panel_shop_product_ids": [
      903001,
      903002,
      903003,
      903004
    ]
  },
  {
    "id": 903100,
    "panel_shop_id": 909003,
    "step": 9,
    "panel_illust_id": 100033,
    "loop": 0,
    "step_reward_type": 33,
    "step_reward_id": 960001,
    "step_reward_quantity": 300,
    "lucky_reward_box_id": 100003,
    "panel_shop_product_ids": [
      903101,
      903102,
      903103,
      903104
    ]
  },
  {
    "id": 903200,
    "panel_shop_id": 909003,
    "step": 10,
    "panel_illust_id": 100034,
    "loop": 0,
    "step_reward_type": 1,
    "step_reward_id": 100002,
    "step_reward_quantity": 500,
    "lucky_reward_box_id": 100003,
    "panel_shop_product_ids": [
      903201,
      903202,
      903203,
      903204
    ]
  },
  {
    "id": 903300,
    "panel_shop_id": 909003,
    "step": 11,
    "panel_illust_id": 100035,
    "loop": 0,
    "step_reward_type": 32,
    "step_reward_id": 950012,
    "step_reward_quantity": 100,
    "lucky_reward_box_id": 100003,
    "panel_shop_product_ids": [
      903301,
      903302,
      903303,
      903304
    ]
  },
  {
    "id": 903400,
    "panel_shop_id": 909003,
    "step": 12,
    "panel_illust_id": 100036,
    "loop": 0,
    "step_reward_type": 33,
    "step_reward_id": 960001,
    "step_reward_quantity": 300,
    "lucky_reward_box_id": 100003,
    "panel_shop_product_ids": [
      903401,
      903402,
      903403,
      903404
    ]
  },
  {
    "id": 903500,
    "panel_shop_id": 909003,
    "step": 13,
    "panel_illust_id": 100037,
    "loop": 0,
    "step_reward_type": 1,
    "step_reward_id": 100002,
    "step_reward_quantity": 500,
    "lucky_reward_box_id": 100003,
    "panel_shop_product_ids": [
      903501,
      903502,
      903503,
      903504
    ]
  },
  {
    "id": 903600,
    "panel_shop_id": 909003,
    "step": 14,
    "panel_illust_id": 100038,
    "loop": 0,
    "step_reward_type": 32,
    "step_reward_id": 950012,
    "step_reward_quantity": 100,
    "lucky_reward_box_id": 100003,
    "panel_shop_product_ids": [
      903601,
      903602,
      903603,
      903604
    ]
  },
  {
    "id": 903700,
    "panel_shop_id": 909003,
    "step": 15,
    "panel_illust_id": 100039,
    "loop": 0,
    "step_reward_type": 33,
    "step_reward_id": 960001,
    "step_reward_quantity": 300,
    "lucky_reward_box_id": 100003,
    "panel_shop_product_ids": [
      903701,
      903702,
      903703,
      903704
    ]
  },
  {
    "id": 903800,
    "panel_shop_id": 909003,
    "step": 16,
    "panel_illust_id": 100040,
    "loop": 0,
    "step_reward_type": 1,
    "step_reward_id": 100002,
    "step_reward_quantity": 500,
    "lucky_reward_box_id": 100003,
    "panel_shop_product_ids": [
      903801,
      903802,
      903803,
      903804
    ]
  },
  {
    "id": 903900,
    "panel_shop_id": 909003,
    "step": 17,
    "panel_illust_id": 0,
    "loop": 1,
    "step_reward_type": 2,
    "step_reward_id": 105001,
    "step_reward_quantity": 5,
    "lucky_reward_box_id": 100003,
    "panel_shop_product_ids": [
      903901,
      903902,
      903903,
      903904
    ]
  },
  {
    "id": 904000,
    "panel_shop_id": 909004,
    "step": 1,
    "panel_illust_id": 100041,
    "loop": 0,
    "step_reward_type": 1,
    "step_reward_id": 100002,
    "step_reward_quantity": 1500,
    "lucky_reward_box_id": 100004,
    "panel_shop_product_ids": [
      904001,
      904002,
      904003,
      904004,
      904005,
      904006,
      904007,
      904008,
      904009,
      904010,
      904011,
      904012,
      904013,
      904014,
      904015,
      904016
    ]
  },
  {
    "id": 904100,
    "panel_shop_id": 909004,
    "step": 2,
    "panel_illust_id": 100042,
    "loop": 0,
    "step_reward_type": 31,
    "step_reward_id": 501406400,
    "step_reward_quantity": 1,
    "lucky_reward_box_id": 100004,
    "panel_shop_product_ids": [
      904101,
      904102,
      904103,
      904104,
      904105,
      904106,
      904107,
      904108,
      904109,
      904110,
      904111,
      904112,
      904113,
      904114,
      904115,
      904116
    ]
  },
  {
    "id": 904200,
    "panel_shop_id": 909004,
    "step": 3,
    "panel_illust_id": 100043,
    "loop": 0,
    "step_reward_type": 20,
    "step_reward_id": 881005,
    "step_reward_quantity": 24,
    "lucky_reward_box_id": 100004,
    "panel_shop_product_ids": [
      904201,
      904202,
      904203,
      904204,
      904205,
      904206,
      904207,
      904208,
      904209
    ]
  },
  {
    "id": 904300,
    "panel_shop_id": 909004,
    "step": 4,
    "panel_illust_id": 100044,
    "loop": 0,
    "step_reward_type": 1,
    "step_reward_id": 100002,
    "step_reward_quantity": 500,
    "lucky_reward_box_id": 100004,
    "panel_shop_product_ids": [
      904301,
      904302,
      904303,
      904304,
      904305,
      904306,
      904307,
      904308,
      904309
    ]
  },
  {
    "id": 904400,
    "panel_shop_id": 909004,
    "step": 5,
    "panel_illust_id": 100045,
    "loop": 0,
    "step_reward_type": 33,
    "step_reward_id": 961001,
    "step_reward_quantity": 1,
    "lucky_reward_box_id": 100004,
    "panel_shop_product_ids": [
      904401,
      904402,
      904403,
      904404,
      904405,
      904406,
      904407,
      904408,
      904409
    ]
  },
  {
    "id": 904500,
    "panel_shop_id": 909004,
    "step": 6,
    "panel_illust_id": 100046,
    "loop": 0,
    "step_reward_type": 8,
    "step_reward_id": 810001,
    "step_reward_quantity": 1,
    "lucky_reward_box_id": 100004,
    "panel_shop_product_ids": [
      904501,
      904502,
      904503,
      904504,
      904505,
      904506,
      904507,
      904508,
      904509
    ]
  },
  {
    "id": 904600,
    "panel_shop_id": 909004,
    "step": 7,
    "panel_illust_id": 100047,
    "loop": 0,
    "step_reward_type": 33,
    "step_reward_id": 960001,
    "step_reward_quantity": 150,
    "lucky_reward_box_id": 100004,
    "panel_shop_product_ids": [
      904601,
      904602,
      904603,
      904604,
      904605,
      904606,
      904607,
      904608,
      904609
    ]
  },
  {
    "id": 904700,
    "panel_shop_id": 909004,
    "step": 8,
    "panel_illust_id": 100048,
    "loop": 0,
    "step_reward_type": 2,
    "step_reward_id": 105001,
    "step_reward_quantity": 50,
    "lucky_reward_box_id": 100004,
    "panel_shop_product_ids": [
      904701,
      904702,
      904703,
      904704,
      904705,
      904706,
      904707,
      904708,
      904709
    ]
  },
  {
    "id": 904800,
    "panel_shop_id": 909004,
    "step": 9,
    "panel_illust_id": 100049,
    "loop": 0,
    "step_reward_type": 33,
    "step_reward_id": 960001,
    "step_reward_quantity": 150,
    "lucky_reward_box_id": 100004,
    "panel_shop_product_ids": [
      904801,
      904802,
      904803,
      904804,
      904805,
      904806,
      904807,
      904808,
      904809
    ]
  },
  {
    "id": 904900,
    "panel_shop_id": 909004,
    "step": 10,
    "panel_illust_id": 100050,
    "loop": 0,
    "step_reward_type": 1,
    "step_reward_id": 100002,
    "step_reward_quantity": 500,
    "lucky_reward_box_id": 100004,
    "panel_shop_product_ids": [
      904901,
      904902,
      904903,
      904904,
      904905,
      904906,
      904907,
      904908,
      904909
    ]
  },
  {
    "id": 905000,
    "panel_shop_id": 909004,
    "step": 11,
    "panel_illust_id": 100051,
    "loop": 0,
    "step_reward_type": 33,
    "step_reward_id": 960001,
    "step_reward_quantity": 150,
    "lucky_reward_box_id": 100004,
    "panel_shop_product_ids": [
      905001,
      905002,
      905003,
      905004,
      905005,
      905006,
      905007,
      905008,
      905009
    ]
  },
  {
    "id": 905100,
    "panel_shop_id": 909004,
    "step": 12,
    "panel_illust_id": 100052,
    "loop": 0,
    "step_reward_type": 2,
    "step_reward_id": 105001,
    "step_reward_quantity": 50,
    "lucky_reward_box_id": 100004,
    "panel_shop_product_ids": [
      905101,
      905102,
      905103,
      905104,
      905105,
      905106,
      905107,
      905108,
      905109
    ]
  },
  {
    "id": 905200,
    "panel_shop_id": 909004,
    "step": 13,
    "panel_illust_id": 100053,
    "loop": 0,
    "step_reward_type": 33,
    "step_reward_id": 960001,
    "step_reward_quantity": 150,
    "lucky_reward_box_id": 100004,
    "panel_shop_product_ids": [
      905201,
      905202,
      905203,
      905204,
      905205,
      905206,
      905207,
      905208,
      905209
    ]
  },
  {
    "id": 905300,
    "panel_shop_id": 909004,
    "step": 14,
    "panel_illust_id": 100054,
    "loop": 0,
    "step_reward_type": 2,
    "step_reward_id": 105001,
    "step_reward_quantity": 50,
    "lucky_reward_box_id": 100004,
    "panel_shop_product_ids": [
      905301,
      905302,
      905303,
      905304,
      905305,
      905306,
      905307,
      905308,
      905309
    ]
  },
  {
    "id": 905400,
    "panel_shop_id": 909004,
    "step": 15,
    "panel_illust_id": 100055,
    "loop": 0,
    "step_reward_type": 1,
    "step_reward_id": 100002,
    "step_reward_quantity": 500,
    "lucky_reward_box_id": 100004,
    "panel_shop_product_ids": [
      905401,
      905402,
      905403,
      905404
    ]
  },
  {
    "id": 905500,
    "panel_shop_id": 909004,
    "step": 16,
    "panel_illust_id": 0,
    "loop": 1,
    "step_reward_type": 2,
    "step_reward_id": 105001,
    "step_reward_quantity": 5,
    "lucky_reward_box_id": 100004,
    "panel_shop_product_ids": [
      905501,
      905502,
      905503,
      905504
    ]
  }
]